{"type":"furniture","name":"easter14_chocchestrare","visualizationType":"furniture_animated","logicType":"furniture_multistate","spritesheet":"easter14_chocchestrare_spritesheet.json","dimensions":{"x":2,"y":1,"z":1.0},"directions":[180,90],"assets":{"easter14_chocchestrare_64_a_4_1":{"x":33,"y":84},"easter14_chocchestrare_64_a_2_3":{"source":"easter14_chocchestrare_64_a_4_3","x":33,"y":84,"flipH":true},"easter14_chocchestrare_32_b_2_0":{"source":"easter14_chocchestrare_32_b_4_0","x":6,"y":20,"flipH":true},"easter14_chocchestrare_64_a_4_2":{"x":33,"y":84},"easter14_chocchestrare_64_a_2_4":{"source":"easter14_chocchestrare_64_a_4_4","x":33,"y":84,"flipH":true},"easter14_chocchestrare_32_b_4_0":{"x":6,"y":20},"easter14_chocchestrare_64_a_2_1":{"source":"easter14_chocchestrare_64_a_4_1","x":33,"y":84,"flipH":true},"easter14_chocchestrare_32_b_2_2":{"source":"easter14_chocchestrare_32_b_4_2","x":6,"y":39,"flipH":true},"easter14_chocchestrare_64_a_4_0":{"x":29,"y":55},"easter14_chocchestrare_64_a_2_2":{"source":"easter14_chocchestrare_64_a_4_2","x":33,"y":84,"flipH":true},"easter14_chocchestrare_32_b_2_1":{"source":"easter14_chocchestrare_32_b_4_1","x":6,"y":39,"flipH":true},"easter14_chocchestrare_64_a_2_0":{"source":"easter14_chocchestrare_64_a_4_0","x":29,"y":55,"flipH":true},"easter14_chocchestrare_64_b_4_3":{"x":32,"y":79},"easter14_chocchestrare_64_b_2_5":{"source":"easter14_chocchestrare_64_b_4_5","x":32,"y":79,"flipH":true},"easter14_chocchestrare_64_b_4_2":{"x":32,"y":79},"easter14_chocchestrare_icon_a":{"x":14,"y":13},"easter14_chocchestrare_64_b_2_4":{"source":"easter14_chocchestrare_64_b_4_4","x":32,"y":79,"flipH":true},"easter14_chocchestrare_64_b_4_5":{"x":32,"y":79},"easter14_chocchestrare_64_b_4_4":{"x":32,"y":79},"easter14_chocchestrare_64_b_2_1":{"source":"easter14_chocchestrare_64_b_4_1","x":33,"y":79,"flipH":true},"easter14_chocchestrare_64_b_2_0":{"source":"easter14_chocchestrare_64_b_4_0","x":12,"y":42,"flipH":true},"easter14_chocchestrare_64_b_4_1":{"x":33,"y":79},"easter14_chocchestrare_64_b_2_3":{"source":"easter14_chocchestrare_64_b_4_3","x":32,"y":79,"flipH":true},"easter14_chocchestrare_64_b_4_0":{"x":12,"y":42},"easter14_chocchestrare_64_b_2_2":{"source":"easter14_chocchestrare_64_b_4_2","x":32,"y":79,"flipH":true},"easter14_chocchestrare_64_a_4_5":{"x":33,"y":84},"easter14_chocchestrare_32_b_4_2":{"x":6,"y":39},"easter14_chocchestrare_32_b_2_4":{"source":"easter14_chocchestrare_32_b_4_4","x":6,"y":39,"flipH":true},"easter14_chocchestrare_32_b_4_1":{"x":6,"y":39},"easter14_chocchestrare_32_b_2_3":{"source":"easter14_chocchestrare_32_b_4_3","x":6,"y":39,"flipH":true},"easter14_chocchestrare_64_a_4_3":{"x":33,"y":84},"easter14_chocchestrare_32_b_4_4":{"x":6,"y":39},"easter14_chocchestrare_64_a_2_5":{"source":"easter14_chocchestrare_64_a_4_5","x":33,"y":84,"flipH":true},"easter14_chocchestrare_64_a_4_4":{"x":33,"y":84},"easter14_chocchestrare_32_b_4_3":{"x":6,"y":39},"easter14_chocchestrare_32_a_4_4":{"x":23,"y":43},"easter14_chocchestrare_32_a_4_2":{"x":23,"y":43},"easter14_chocchestrare_32_a_2_4":{"source":"easter14_chocchestrare_32_a_4_4","x":23,"y":43,"flipH":true},"easter14_chocchestrare_32_a_4_3":{"x":23,"y":43},"easter14_chocchestrare_32_a_4_0":{"x":15,"y":27},"easter14_chocchestrare_32_a_2_2":{"source":"easter14_chocchestrare_32_a_4_2","x":23,"y":43,"flipH":true},"easter14_chocchestrare_32_a_4_1":{"x":23,"y":43},"easter14_chocchestrare_32_a_2_3":{"source":"easter14_chocchestrare_32_a_4_3","x":23,"y":43,"flipH":true},"easter14_chocchestrare_32_a_2_0":{"source":"easter14_chocchestrare_32_a_4_0","x":15,"y":27,"flipH":true},"easter14_chocchestrare_32_a_2_1":{"source":"easter14_chocchestrare_32_a_4_1","x":23,"y":43,"flipH":true}},"visualization":{"layerCount":2,"angle":45,"layers":{"0":{},"1":{"z":1000.0}},"animations":{"0":{"layers":{}},"1":{"layers":{"0":{"loopCount":0,"frameRepeat":4,"frames":[1,2,3,4,5]},"1":{"loopCount":0,"frameRepeat":4,"frames":[1,2,3,4,5]}}}}}}