{
	"meta": {
		"image": "easter_c19_book4_sheet.png",
		"size": {"w":388,"h":417},
		"scale": "1"
	},
	"frames": {
		"easter_c19_book4_11.png":
		{
			"frame": {"x":0,"y":0,"w":97,"h":417},
			"rotated": false,
			"trimmed": false,
			"spriteSourceSize": {"x":0,"y":0,"w":97,"h":417},
			"sourceSize": {"w":97,"h":417}
		},
		"easter_c19_book4_3.png":
		{
			"frame": {"x":97,"y":0,"w":97,"h":364},
			"rotated": false,
			"trimmed": false,
			"spriteSourceSize": {"x":0,"y":0,"w":97,"h":364},
			"sourceSize": {"w":97,"h":364}
		},
		"easter_c19_book4_5.png":
		{
			"frame": {"x":194,"y":0,"w":97,"h":233},
			"rotated": false,
			"trimmed": false,
			"spriteSourceSize": {"x":0,"y":0,"w":97,"h":233},
			"sourceSize": {"w":97,"h":233}
		},
		"easter_c19_book4_10.png":
		{
			"frame": {"x":194,"y":233,"w":97,"h":151},
			"rotated": false,
			"trimmed": false,
			"spriteSourceSize": {"x":0,"y":0,"w":97,"h":151},
			"sourceSize": {"w":97,"h":151}
		},
		"easter_c19_book4_1.png":
		{
			"frame": {"x":291,"y":0,"w":97,"h":70},
			"rotated": false,
			"trimmed": false,
			"spriteSourceSize": {"x":0,"y":0,"w":97,"h":70},
			"sourceSize": {"w":97,"h":70}
		},
		"easter_c19_book4_15.png":
		{
			"frame": {"x":291,"y":70,"w":97,"h":70},
			"rotated": false,
			"trimmed": false,
			"spriteSourceSize": {"x":0,"y":0,"w":97,"h":70},
			"sourceSize": {"w":97,"h":70}
		},
		"easter_c19_book4_2.png":
		{
			"frame": {"x":291,"y":140,"w":97,"h":70},
			"rotated": false,
			"trimmed": false,
			"spriteSourceSize": {"x":0,"y":0,"w":97,"h":70},
			"sourceSize": {"w":97,"h":70}
		},
		"easter_c19_book4_13.png":
		{
			"frame": {"x":291,"y":210,"w":78,"h":49},
			"rotated": false,
			"trimmed": false,
			"spriteSourceSize": {"x":0,"y":0,"w":78,"h":49},
			"sourceSize": {"w":78,"h":49}
		},
		"easter_c19_book4_14.png":
		{
			"frame": {"x":291,"y":259,"w":76,"h":62},
			"rotated": false,
			"trimmed": false,
			"spriteSourceSize": {"x":0,"y":0,"w":76,"h":62},
			"sourceSize": {"w":76,"h":62}
		},
		"easter_c19_book4_9.png":
		{
			"frame": {"x":291,"y":321,"w":63,"h":71},
			"rotated": false,
			"trimmed": false,
			"spriteSourceSize": {"x":0,"y":0,"w":63,"h":71},
			"sourceSize": {"w":63,"h":71}
		},
		"easter_c19_book4_8.png":
		{
			"frame": {"x":97,"y":364,"w":63,"h":41},
			"rotated": false,
			"trimmed": false,
			"spriteSourceSize": {"x":0,"y":0,"w":63,"h":41},
			"sourceSize": {"w":63,"h":41}
		},
		"easter_c19_book4_12.png":
		{
			"frame": {"x":194,"y":384,"w":62,"h":32},
			"rotated": false,
			"trimmed": false,
			"spriteSourceSize": {"x":0,"y":0,"w":62,"h":32},
			"sourceSize": {"w":62,"h":32}
		},
		"easter_c19_book4_4.png":
		{
			"frame": {"x":354,"y":321,"w":29,"h":19},
			"rotated": false,
			"trimmed": false,
			"spriteSourceSize": {"x":0,"y":0,"w":29,"h":19},
			"sourceSize": {"w":29,"h":19}
		}
	}
}