{"type":"furniture","name":"ny2013_cup","visualizationType":"furniture_static","logicType":"furniture_basic","spritesheet":"ny2013_cup_spritesheet.json","dimensions":{"x":1,"y":1,"z":0.0},"directions":[0,90],"assets":{"ny2013_cup_64_a_0_0":{"x":10,"y":18},"ny2013_cup_32_a_0_0":{"x":5,"y":9},"ny2013_cup_64_a_2_0":{"source":"ny2013_cup_64_a_0_0","x":10,"y":18,"flipH":true},"ny2013_cup_32_a_2_0":{"source":"ny2013_cup_32_a_0_0","x":5,"y":9,"flipH":true},"ny2013_cup_icon_a":{"x":10,"y":18}},"visualization":{"layerCount":1,"angle":45,"layers":{"0":{"z":10.0}}}}