{"type":"furniture","name":"tiki_tray2","visualizationType":"furniture_static","logicType":"furniture_basic","spritesheet":"tiki_tray2_spritesheet.json","dimensions":{"x":1,"y":1,"z":0.0},"directions":[0,90],"assets":{"tiki_tray2_icon_a":{"x":11,"y":11},"tiki_tray2_32_a_0_0":{"x":11,"y":17},"tiki_tray2_64_sd_0_0":{"x":18,"y":-3},"tiki_tray2_32_sd_0_0":{"x":9,"y":-2},"tiki_tray2_64_a_2_0":{"source":"tiki_tray2_64_a_0_0","x":23,"y":39,"flipH":true},"tiki_tray2_64_sd_2_0":{"source":"tiki_tray2_64_sd_0_0","x":18,"y":-3,"flipH":true},"tiki_tray2_32_sd_2_0":{"source":"tiki_tray2_32_sd_0_0","x":9,"y":-2,"flipH":true},"tiki_tray2_64_a_0_0":{"x":23,"y":39},"tiki_tray2_32_a_2_0":{"source":"tiki_tray2_32_a_0_0","x":11,"y":17,"flipH":true}},"visualization":{"layerCount":1,"angle":45}}