[
  {
    "code": 36,
    "characterId": 1,
    "imgType": "png",
    "imageName": "ads_calip_pool_1.png"
  },
  {
    "code": 36,
    "characterId": 3,
    "imgType": "png",
    "imageName": "ads_calip_pool_3.png"
  },
  {
    "code": 36,
    "characterId": 4,
    "imgType": "png",
    "imageName": "ads_calip_pool_4.png"
  },
  {
    "code": 36,
    "characterId": 5,
    "imgType": "png",
    "imageName": "ads_calip_pool_5.png"
  },
  {
    "code": 36,
    "characterId": 6,
    "imgType": "png",
    "imageName": "ads_calip_pool_6.png"
  },
  {
    "code": 36,
    "characterId": 7,
    "imgType": "png",
    "imageName": "ads_calip_pool_7.png"
  },
  {
    "code": 36,
    "characterId": 8,
    "imgType": "png",
    "imageName": "ads_calip_pool_8.png"
  },
  {
    "code": 36,
    "characterId": 10,
    "imgType": "png",
    "imageName": "ads_calip_pool_10.png"
  },
  {
    "code": 36,
    "characterId": 12,
    "imgType": "png",
    "imageName": "ads_calip_pool_12.png"
  },
  {
    "code": 36,
    "characterId": 13,
    "imgType": "png",
    "imageName": "ads_calip_pool_13.png"
  },
  {
    "code": 36,
    "characterId": 14,
    "imgType": "png",
    "imageName": "ads_calip_pool_14.png"
  },
  {
    "code": 36,
    "characterId": 15,
    "imgType": "png",
    "imageName": "ads_calip_pool_15.png"
  },
  {
    "code": 36,
    "characterId": 16,
    "imgType": "png",
    "imageName": "ads_calip_pool_16.png"
  },
  {
    "code": 36,
    "characterId": 17,
    "imgType": "png",
    "imageName": "ads_calip_pool_17.png"
  },
  {
    "code": 36,
    "characterId": 19,
    "imgType": "png",
    "imageName": "ads_calip_pool_19.png"
  },
  {
    "code": 36,
    "characterId": 20,
    "imgType": "png",
    "imageName": "ads_calip_pool_20.png"
  },
  {
    "code": 36,
    "characterId": 21,
    "imgType": "png",
    "imageName": "ads_calip_pool_21.png"
  },
  {
    "code": 36,
    "characterId": 23,
    "imgType": "png",
    "imageName": "ads_calip_pool_23.png"
  },
  {
    "code": 36,
    "characterId": 24,
    "imgType": "png",
    "imageName": "ads_calip_pool_24.png"
  }
]