{
	"meta": {
		"image": "penguin_basic_sheet.png",
		"size": {"w":240,"h":224},
		"scale": "1"
	},
	"frames": {
		"penguin_basic_sheet.png":
		{
			"frame": {"x":0,"y":0,"w":179,"h":149},
			"rotated": false,
			"trimmed": false,
			"spriteSourceSize": {"x":0,"y":0,"w":179,"h":149},
			"sourceSize": {"w":179,"h":149}
		},
		"penguin_basic_9.png":
		{
			"frame": {"x":179,"y":0,"w":41,"h":59},
			"rotated": false,
			"trimmed": false,
			"spriteSourceSize": {"x":0,"y":0,"w":41,"h":59},
			"sourceSize": {"w":41,"h":59}
		},
		"penguin_basic_10.png":
		{
			"frame": {"x":179,"y":59,"w":39,"h":59},
			"rotated": false,
			"trimmed": false,
			"spriteSourceSize": {"x":0,"y":0,"w":39,"h":59},
			"sourceSize": {"w":39,"h":59}
		},
		"penguin_basic_13.png":
		{
			"frame": {"x":0,"y":149,"w":37,"h":59},
			"rotated": false,
			"trimmed": false,
			"spriteSourceSize": {"x":0,"y":0,"w":37,"h":59},
			"sourceSize": {"w":37,"h":59}
		},
		"penguin_basic_14.png":
		{
			"frame": {"x":37,"y":149,"w":33,"h":59},
			"rotated": false,
			"trimmed": false,
			"spriteSourceSize": {"x":0,"y":0,"w":33,"h":59},
			"sourceSize": {"w":33,"h":59}
		},
		"penguin_basic_15.png":
		{
			"frame": {"x":70,"y":149,"w":32,"h":59},
			"rotated": false,
			"trimmed": false,
			"spriteSourceSize": {"x":0,"y":0,"w":32,"h":59},
			"sourceSize": {"w":32,"h":59}
		},
		"penguin_basic_17.png":
		{
			"frame": {"x":102,"y":149,"w":32,"h":59},
			"rotated": false,
			"trimmed": false,
			"spriteSourceSize": {"x":0,"y":0,"w":32,"h":59},
			"sourceSize": {"w":32,"h":59}
		},
		"penguin_basic_18.png":
		{
			"frame": {"x":134,"y":149,"w":32,"h":59},
			"rotated": false,
			"trimmed": false,
			"spriteSourceSize": {"x":0,"y":0,"w":32,"h":59},
			"sourceSize": {"w":32,"h":59}
		},
		"penguin_basic_16.png":
		{
			"frame": {"x":166,"y":149,"w":32,"h":57},
			"rotated": false,
			"trimmed": false,
			"spriteSourceSize": {"x":0,"y":0,"w":32,"h":57},
			"sourceSize": {"w":32,"h":57}
		},
		"penguin_basic_1.png":
		{
			"frame": {"x":179,"y":118,"w":22,"h":31},
			"rotated": false,
			"trimmed": false,
			"spriteSourceSize": {"x":0,"y":0,"w":22,"h":31},
			"sourceSize": {"w":22,"h":31}
		},
		"penguin_basic_3.png":
		{
			"frame": {"x":198,"y":149,"w":22,"h":31},
			"rotated": false,
			"trimmed": false,
			"spriteSourceSize": {"x":0,"y":0,"w":22,"h":31},
			"sourceSize": {"w":22,"h":31}
		},
		"penguin_basic_7.png":
		{
			"frame": {"x":220,"y":0,"w":20,"h":31},
			"rotated": false,
			"trimmed": false,
			"spriteSourceSize": {"x":0,"y":0,"w":20,"h":31},
			"sourceSize": {"w":20,"h":31}
		},
		"penguin_basic_20.png":
		{
			"frame": {"x":220,"y":31,"w":17,"h":31},
			"rotated": false,
			"trimmed": false,
			"spriteSourceSize": {"x":0,"y":0,"w":17,"h":31},
			"sourceSize": {"w":17,"h":31}
		},
		"penguin_basic_4.png":
		{
			"frame": {"x":220,"y":62,"w":17,"h":31},
			"rotated": false,
			"trimmed": false,
			"spriteSourceSize": {"x":0,"y":0,"w":17,"h":31},
			"sourceSize": {"w":17,"h":31}
		},
		"penguin_basic_5.png":
		{
			"frame": {"x":220,"y":93,"w":17,"h":31},
			"rotated": false,
			"trimmed": false,
			"spriteSourceSize": {"x":0,"y":0,"w":17,"h":31},
			"sourceSize": {"w":17,"h":31}
		},
		"penguin_basic_6.png":
		{
			"frame": {"x":220,"y":124,"w":17,"h":31},
			"rotated": false,
			"trimmed": false,
			"spriteSourceSize": {"x":0,"y":0,"w":17,"h":31},
			"sourceSize": {"w":17,"h":31}
		},
		"penguin_basic_12.png":
		{
			"frame": {"x":220,"y":155,"w":17,"h":30},
			"rotated": false,
			"trimmed": false,
			"spriteSourceSize": {"x":0,"y":0,"w":17,"h":30},
			"sourceSize": {"w":17,"h":30}
		},
		"penguin_basic_2.png":
		{
			"frame": {"x":201,"y":118,"w":17,"h":30},
			"rotated": false,
			"trimmed": false,
			"spriteSourceSize": {"x":0,"y":0,"w":17,"h":30},
			"sourceSize": {"w":17,"h":30}
		},
		"penguin_basic_19.png":
		{
			"frame": {"x":0,"y":208,"w":29,"h":16},
			"rotated": false,
			"trimmed": false,
			"spriteSourceSize": {"x":0,"y":0,"w":29,"h":16},
			"sourceSize": {"w":29,"h":16}
		},
		"penguin_basic_22.png":
		{
			"frame": {"x":220,"y":185,"w":16,"h":8},
			"rotated": false,
			"trimmed": false,
			"spriteSourceSize": {"x":0,"y":0,"w":16,"h":8},
			"sourceSize": {"w":16,"h":8}
		}
	}
}