{"meta":{"app":"FFConverter ~ Joopie","format":"RGBA8888","image":"room_thr15_cover.png","scale":"1.0","size":{"w":256,"h":512},"version":"1.0"},"frames":{"room_thr15_cover_room_thr15_cover_64_b_0_0.png":{"frame":{"x":2,"y":2,"w":94,"h":76},"sourceSize":{"w":94,"h":76},"spriteSourceSize":{"x":0,"y":0,"w":94,"h":76},"rotated":false,"trimmed":false},"room_thr15_cover_room_thr15_cover_64_a_0_0.png":{"frame":{"x":98,"y":237,"w":96,"h":135},"sourceSize":{"w":96,"h":135},"spriteSourceSize":{"x":0,"y":0,"w":96,"h":135},"rotated":false,"trimmed":false},"room_thr15_cover_room_thr15_cover_icon_a.png":{"frame":{"x":196,"y":346,"w":23,"h":26},"sourceSize":{"w":23,"h":26},"spriteSourceSize":{"x":0,"y":0,"w":23,"h":26},"rotated":false,"trimmed":false},"room_thr15_cover_room_thr15_cover_64_d_0_0.png":{"frame":{"x":98,"y":160,"w":94,"h":75},"sourceSize":{"w":94,"h":75},"spriteSourceSize":{"x":0,"y":0,"w":94,"h":75},"rotated":false,"trimmed":false},"room_thr15_cover_room_thr15_cover_64_sd_0_0.png":{"frame":{"x":2,"y":374,"w":250,"h":125},"sourceSize":{"w":250,"h":125},"spriteSourceSize":{"x":0,"y":0,"w":250,"h":125},"rotated":false,"trimmed":false},"room_thr15_cover_room_thr15_cover_64_e_0_0.png":{"frame":{"x":93,"y":84,"w":92,"h":74},"sourceSize":{"w":92,"h":74},"spriteSourceSize":{"x":0,"y":0,"w":92,"h":74},"rotated":false,"trimmed":false},"room_thr15_cover_room_thr15_cover_64_c_0_0.png":{"frame":{"x":2,"y":226,"w":94,"h":146},"sourceSize":{"w":94,"h":146},"spriteSourceSize":{"x":0,"y":0,"w":94,"h":146},"rotated":false,"trimmed":false},"room_thr15_cover_room_thr15_cover_64_f_0_0.png":{"frame":{"x":2,"y":80,"w":89,"h":144},"sourceSize":{"w":89,"h":144},"spriteSourceSize":{"x":0,"y":0,"w":89,"h":144},"rotated":false,"trimmed":false}}}