{
	"meta": {
		"image": "ads_antena3_wall_sheet.png",
		"size": {"w":308,"h":148},
		"scale": "1"
	},
	"frames": {
		"ads_antena3_wall_sheet.png":
		{
			"frame": {"x":0,"y":0,"w":154,"h":148},
			"rotated": false,
			"trimmed": false,
			"spriteSourceSize": {"x":0,"y":0,"w":154,"h":148},
			"sourceSize": {"w":154,"h":148}
		},
		"ads_antena3_wall_2.png":
		{
			"frame": {"x":154,"y":0,"w":77,"h":98},
			"rotated": false,
			"trimmed": false,
			"spriteSourceSize": {"x":0,"y":0,"w":77,"h":98},
			"sourceSize": {"w":77,"h":98}
		},
		"ads_antena3_wall_8.png":
		{
			"frame": {"x":231,"y":0,"w":77,"h":98},
			"rotated": false,
			"trimmed": false,
			"spriteSourceSize": {"x":0,"y":0,"w":77,"h":98},
			"sourceSize": {"w":77,"h":98}
		},
		"ads_antena3_wall_9.png":
		{
			"frame": {"x":231,"y":98,"w":40,"h":50},
			"rotated": false,
			"trimmed": false,
			"spriteSourceSize": {"x":0,"y":0,"w":40,"h":50},
			"sourceSize": {"w":40,"h":50}
		},
		"ads_antena3_wall_5.png":
		{
			"frame": {"x":154,"y":98,"w":39,"h":50},
			"rotated": false,
			"trimmed": false,
			"spriteSourceSize": {"x":0,"y":0,"w":39,"h":50},
			"sourceSize": {"w":39,"h":50}
		},
		"ads_antena3_wall_6.png":
		{
			"frame": {"x":271,"y":98,"w":30,"h":29},
			"rotated": false,
			"trimmed": false,
			"spriteSourceSize": {"x":0,"y":0,"w":30,"h":29},
			"sourceSize": {"w":30,"h":29}
		}
	}
}