[
  {
    "code": 36,
    "characterId": 1,
    "imgType": "png",
    "imageName": "track12_tea_mother_1.png"
  },
  {
    "code": 36,
    "characterId": 2,
    "imgType": "png",
    "imageName": "track12_tea_mother_2.png"
  },
  {
    "code": 36,
    "characterId": 3,
    "imgType": "png",
    "imageName": "track12_tea_mother_3.png"
  },
  {
    "code": 36,
    "characterId": 6,
    "imgType": "png",
    "imageName": "track12_tea_mother_6.png"
  },
  {
    "code": 36,
    "characterId": 8,
    "imgType": "png",
    "imageName": "track12_tea_mother_8.png"
  },
  {
    "code": 36,
    "characterId": 9,
    "imgType": "png",
    "imageName": "track12_tea_mother_9.png"
  },
  {
    "code": 36,
    "characterId": 10,
    "imgType": "png",
    "imageName": "track12_tea_mother_10.png"
  },
  {
    "code": 36,
    "characterId": 11,
    "imgType": "png",
    "imageName": "track12_tea_mother_11.png"
  },
  {
    "code": 36,
    "characterId": 14,
    "imgType": "png",
    "imageName": "track12_tea_mother_14.png"
  }
]