{"meta":{"app":"FFConverter ~ Joopie","format":"RGBA8888","image":"party_seat.png","scale":"1.0","size":{"w":512,"h":64},"version":"1.0"},"frames":{"party_seat_party_seat_32_b_0_0.png":{"frame":{"x":368,"y":21,"w":18,"h":10},"sourceSize":{"w":18,"h":10},"spriteSourceSize":{"x":0,"y":0,"w":18,"h":10},"rotated":false,"trimmed":false},"party_seat_party_seat_32_c_0_0.png":{"frame":{"x":473,"y":49,"w":12,"h":13},"sourceSize":{"w":12,"h":13},"spriteSourceSize":{"x":0,"y":0,"w":12,"h":13},"rotated":false,"trimmed":false},"party_seat_party_seat_64_d_0_0.png":{"frame":{"x":417,"y":42,"w":20,"h":20},"sourceSize":{"w":20,"h":20},"spriteSourceSize":{"x":0,"y":0,"w":20,"h":20},"rotated":false,"trimmed":false},"party_seat_party_seat_64_b_0_0.png":{"frame":{"x":142,"y":2,"w":37,"h":19},"sourceSize":{"w":37,"h":19},"spriteSourceSize":{"x":0,"y":0,"w":37,"h":19},"rotated":false,"trimmed":false},"party_seat_party_seat_icon_a.png":{"frame":{"x":368,"y":33,"w":22,"h":29},"sourceSize":{"w":22,"h":29},"spriteSourceSize":{"x":0,"y":0,"w":22,"h":29},"rotated":false,"trimmed":false},"party_seat_party_seat_32_a_0_0.png":{"frame":{"x":318,"y":33,"w":24,"h":29},"sourceSize":{"w":24,"h":29},"spriteSourceSize":{"x":0,"y":0,"w":24,"h":29},"rotated":false,"trimmed":false},"party_seat_party_seat_32_d_0_0.png":{"frame":{"x":205,"y":30,"w":10,"h":10},"sourceSize":{"w":10,"h":10},"spriteSourceSize":{"x":0,"y":0,"w":10,"h":10},"rotated":false,"trimmed":false},"party_seat_party_seat_32_e_0_0.png":{"frame":{"x":263,"y":39,"w":26,"h":23},"sourceSize":{"w":26,"h":23},"spriteSourceSize":{"x":0,"y":0,"w":26,"h":23},"rotated":false,"trimmed":false},"party_seat_party_seat_64_b_2_0.png":{"frame":{"x":142,"y":23,"w":35,"h":39},"sourceSize":{"w":35,"h":39},"spriteSourceSize":{"x":0,"y":0,"w":35,"h":39},"rotated":false,"trimmed":false},"party_seat_party_seat_64_e_0_0.png":{"frame":{"x":94,"y":22,"w":46,"h":40},"sourceSize":{"w":46,"h":40},"spriteSourceSize":{"x":0,"y":0,"w":46,"h":40},"rotated":false,"trimmed":false},"party_seat_party_seat_64_a_0_0.png":{"frame":{"x":2,"y":7,"w":45,"h":55},"sourceSize":{"w":45,"h":55},"spriteSourceSize":{"x":0,"y":0,"w":45,"h":55},"rotated":false,"trimmed":false},"party_seat_party_seat_32_b_2_0.png":{"frame":{"x":439,"y":41,"w":18,"h":21},"sourceSize":{"w":18,"h":21},"spriteSourceSize":{"x":0,"y":0,"w":18,"h":21},"rotated":false,"trimmed":false},"party_seat_party_seat_32_c_2_0.png":{"frame":{"x":459,"y":36,"w":12,"h":26},"sourceSize":{"w":12,"h":26},"spriteSourceSize":{"x":0,"y":0,"w":12,"h":26},"rotated":false,"trimmed":false},"party_seat_party_seat_64_c_2_0.png":{"frame":{"x":344,"y":12,"w":22,"h":50},"sourceSize":{"w":22,"h":50},"spriteSourceSize":{"x":0,"y":0,"w":22,"h":50},"rotated":false,"trimmed":false},"party_seat_party_seat_32_e_2_0.png":{"frame":{"x":291,"y":36,"w":25,"h":26},"sourceSize":{"w":25,"h":26},"spriteSourceSize":{"x":0,"y":0,"w":25,"h":26},"rotated":false,"trimmed":false},"party_seat_party_seat_64_d_2_0.png":{"frame":{"x":2,"y":4,"w":1,"h":1},"sourceSize":{"w":1,"h":1},"spriteSourceSize":{"x":0,"y":0,"w":1,"h":1},"rotated":false,"trimmed":false},"party_seat_party_seat_64_sd_0_0.png":{"frame":{"x":221,"y":42,"w":40,"h":20},"sourceSize":{"w":40,"h":20},"spriteSourceSize":{"x":0,"y":0,"w":40,"h":20},"rotated":false,"trimmed":false},"party_seat_party_seat_64_e_2_0.png":{"frame":{"x":49,"y":15,"w":43,"h":47},"sourceSize":{"w":43,"h":47},"spriteSourceSize":{"x":0,"y":0,"w":43,"h":47},"rotated":false,"trimmed":false},"party_seat_party_seat_64_sd_2_0.png":{"frame":{"x":179,"y":42,"w":40,"h":20},"sourceSize":{"w":40,"h":20},"spriteSourceSize":{"x":0,"y":0,"w":40,"h":20},"rotated":false,"trimmed":false},"party_seat_party_seat_32_sd_0_0.png":{"frame":{"x":179,"y":28,"w":24,"h":12},"sourceSize":{"w":24,"h":12},"spriteSourceSize":{"x":0,"y":0,"w":24,"h":12},"rotated":false,"trimmed":false},"party_seat_party_seat_64_c_0_0.png":{"frame":{"x":392,"y":37,"w":23,"h":25},"sourceSize":{"w":23,"h":25},"spriteSourceSize":{"x":0,"y":0,"w":23,"h":25},"rotated":false,"trimmed":false}}}