{"meta":{"app":"FFConverter ~ Joopie","format":"RGBA8888","image":"horse_trough.png","scale":"1.0","size":{"w":512,"h":64},"version":"1.0"},"frames":{"horse_trough_horse_trough_32_a_2_5.png":{"frame":{"x":324,"y":40,"w":22,"h":18},"sourceSize":{"w":22,"h":18},"spriteSourceSize":{"x":0,"y":0,"w":22,"h":18},"rotated":false,"trimmed":false},"horse_trough_horse_trough_64_a_2_0.png":{"frame":{"x":90,"y":24,"w":42,"h":34},"sourceSize":{"w":42,"h":34},"spriteSourceSize":{"x":0,"y":0,"w":42,"h":34},"rotated":false,"trimmed":false},"horse_trough_horse_trough_icon_a.png":{"frame":{"x":266,"y":32,"w":32,"h":26},"sourceSize":{"w":32,"h":26},"spriteSourceSize":{"x":0,"y":0,"w":32,"h":26},"rotated":false,"trimmed":false},"horse_trough_horse_trough_64_a_2_3.png":{"frame":{"x":46,"y":24,"w":42,"h":34},"sourceSize":{"w":42,"h":34},"spriteSourceSize":{"x":0,"y":0,"w":42,"h":34},"rotated":false,"trimmed":false},"horse_trough_horse_trough_64_a_2_5.png":{"frame":{"x":222,"y":24,"w":42,"h":34},"sourceSize":{"w":42,"h":34},"spriteSourceSize":{"x":0,"y":0,"w":42,"h":34},"rotated":false,"trimmed":false},"horse_trough_horse_trough_32_sd_2_0.png":{"frame":{"x":115,"y":11,"w":20,"h":11},"sourceSize":{"w":20,"h":11},"spriteSourceSize":{"x":0,"y":0,"w":20,"h":11},"rotated":false,"trimmed":false},"horse_trough_horse_trough_64_a_2_1.png":{"frame":{"x":134,"y":24,"w":42,"h":34},"sourceSize":{"w":42,"h":34},"spriteSourceSize":{"x":0,"y":0,"w":42,"h":34},"rotated":false,"trimmed":false},"horse_trough_horse_trough_32_a_2_3.png":{"frame":{"x":91,"y":4,"w":22,"h":18},"sourceSize":{"w":22,"h":18},"spriteSourceSize":{"x":0,"y":0,"w":22,"h":18},"rotated":false,"trimmed":false},"horse_trough_horse_trough_32_a_2_1.png":{"frame":{"x":43,"y":4,"w":22,"h":18},"sourceSize":{"w":22,"h":18},"spriteSourceSize":{"x":0,"y":0,"w":22,"h":18},"rotated":false,"trimmed":false},"horse_trough_horse_trough_32_a_2_4.png":{"frame":{"x":348,"y":40,"w":22,"h":18},"sourceSize":{"w":22,"h":18},"spriteSourceSize":{"x":0,"y":0,"w":22,"h":18},"rotated":false,"trimmed":false},"horse_trough_horse_trough_64_sd_2_0.png":{"frame":{"x":2,"y":2,"w":39,"h":20},"sourceSize":{"w":39,"h":20},"spriteSourceSize":{"x":0,"y":0,"w":39,"h":20},"rotated":false,"trimmed":false},"horse_trough_horse_trough_64_a_2_4.png":{"frame":{"x":178,"y":24,"w":42,"h":34},"sourceSize":{"w":42,"h":34},"spriteSourceSize":{"x":0,"y":0,"w":42,"h":34},"rotated":false,"trimmed":false},"horse_trough_horse_trough_32_a_2_2.png":{"frame":{"x":300,"y":40,"w":22,"h":18},"sourceSize":{"w":22,"h":18},"spriteSourceSize":{"x":0,"y":0,"w":22,"h":18},"rotated":false,"trimmed":false},"horse_trough_horse_trough_64_a_2_2.png":{"frame":{"x":2,"y":24,"w":42,"h":34},"sourceSize":{"w":42,"h":34},"spriteSourceSize":{"x":0,"y":0,"w":42,"h":34},"rotated":false,"trimmed":false},"horse_trough_horse_trough_32_a_2_0.png":{"frame":{"x":67,"y":4,"w":22,"h":18},"sourceSize":{"w":22,"h":18},"spriteSourceSize":{"x":0,"y":0,"w":22,"h":18},"rotated":false,"trimmed":false}}}