[
  {
    "code": 36,
    "characterId": 1,
    "imgType": "png",
    "imageName": "gardening_box_1.png"
  },
  {
    "code": 36,
    "characterId": 4,
    "imgType": "png",
    "imageName": "gardening_box_4.png"
  },
  {
    "code": 36,
    "characterId": 5,
    "imgType": "png",
    "imageName": "gardening_box_5.png"
  },
  {
    "code": 36,
    "characterId": 6,
    "imgType": "png",
    "imageName": "gardening_box_6.png"
  },
  {
    "code": 36,
    "characterId": 10,
    "imgType": "png",
    "imageName": "gardening_box_10.png"
  }
]