{"meta":{"app":"FFConverter ~ Joopie","format":"RGBA8888","image":"room_info15_gate.png","scale":"1.0","size":{"w":64,"h":128},"version":"1.0"},"frames":{"room_info15_gate_room_info15_gate_64_b_2_0.png":{"frame":{"x":2,"y":45,"w":33,"h":44},"sourceSize":{"w":33,"h":44},"spriteSourceSize":{"x":0,"y":0,"w":33,"h":44},"rotated":false,"trimmed":false},"room_info15_gate_room_info15_gate_64_c_2_1.png":{"frame":{"x":42,"y":95,"w":17,"h":31},"sourceSize":{"w":17,"h":31},"spriteSourceSize":{"x":0,"y":0,"w":17,"h":31},"rotated":false,"trimmed":false},"room_info15_gate_room_info15_gate_64_a_0_0.png":{"frame":{"x":42,"y":83,"w":16,"h":10},"sourceSize":{"w":16,"h":10},"spriteSourceSize":{"x":0,"y":0,"w":16,"h":10},"rotated":false,"trimmed":false},"room_info15_gate_room_info15_gate_64_a_2_0.png":{"frame":{"x":37,"y":59,"w":16,"h":10},"sourceSize":{"w":16,"h":10},"spriteSourceSize":{"x":0,"y":0,"w":16,"h":10},"rotated":false,"trimmed":false},"room_info15_gate_room_info15_gate_64_c_2_0.png":{"frame":{"x":2,"y":91,"w":38,"h":35},"sourceSize":{"w":38,"h":35},"spriteSourceSize":{"x":0,"y":0,"w":38,"h":35},"rotated":false,"trimmed":false},"room_info15_gate_room_info15_gate_64_d_2_1.png":{"frame":{"x":37,"y":32,"w":13,"h":13},"sourceSize":{"w":13,"h":13},"spriteSourceSize":{"x":0,"y":0,"w":13,"h":13},"rotated":false,"trimmed":false},"room_info15_gate_room_info15_gate_64_a_6_0.png":{"frame":{"x":37,"y":71,"w":16,"h":10},"sourceSize":{"w":16,"h":10},"spriteSourceSize":{"x":0,"y":0,"w":16,"h":10},"rotated":false,"trimmed":false},"room_info15_gate_room_info15_gate_64_a_4_0.png":{"frame":{"x":37,"y":47,"w":16,"h":10},"sourceSize":{"w":16,"h":10},"spriteSourceSize":{"x":0,"y":0,"w":16,"h":10},"rotated":false,"trimmed":false},"room_info15_gate_room_info15_gate_64_d_2_0.png":{"frame":{"x":47,"y":17,"w":13,"h":13},"sourceSize":{"w":13,"h":13},"spriteSourceSize":{"x":0,"y":0,"w":13,"h":13},"rotated":false,"trimmed":false},"room_info15_gate_room_info15_gate_icon_a.png":{"frame":{"x":15,"y":2,"w":30,"h":28},"sourceSize":{"w":30,"h":28},"spriteSourceSize":{"x":0,"y":0,"w":30,"h":28},"rotated":false,"trimmed":false},"room_info15_gate_room_info15_gate_64_b_2_1.png":{"frame":{"x":2,"y":12,"w":11,"h":31},"sourceSize":{"w":11,"h":31},"spriteSourceSize":{"x":0,"y":0,"w":11,"h":31},"rotated":false,"trimmed":false}}}